simple_template.py
simple_template-1.0.dist-info/LICENCE
simple_template-1.0.dist-info/METADATA
simple_template-1.0.dist-info/WHEEL
simple_template-1.0.dist-info/top_level.txt
simple_template-1.0.dist-info/RECORD
