Metadata-Version: 2.1
Name: simple_template
Version: 1.0
Summary: Simple placeholder filling template library.
Author: James Frost
License: 0BSD
Project-URL: Source, https://github.com/Fraetor/simple_template
Classifier: License :: OSI Approved :: Zero-Clause BSD (0BSD)
Classifier: Topic :: Text Processing
Requires-Python: >=3.8
License-File: LICENCE
